combustivel/__init__.py
combustivel/calc_combustivel.py
combustivel-0.0.2.dist-info/METADATA
combustivel-0.0.2.dist-info/WHEEL
combustivel-0.0.2.dist-info/top_level.txt
combustivel-0.0.2.dist-info/RECORD
