Metadata-Version: 2.1
Name: combustivel
Version: 0.0.2
Home-page: https://github.com/samuelfabiano/desafio-criar-pacotes.git
Author: Samuel
Author-email: samufabiano@yahoo.com.br
Requires-Python: >=3.8
